{"format":"Transformational debugger info","version":1,
"info":{"name":"FmiTest.Model","description":""},
"variables":{
"c.v":{"comment":"Voltage drop of the two pins (= p.v - n.v)","kind":"state","type":"Real","unit":"V","displayUnit":"","source":{"info":{"file":"/usr/lib/omlibrary/Modelica 3.2.3/Electrical/Analog/Interfaces.mo","lineStart":172,"lineEnd":172,"colStart":5,"colEnd":62},"within":["Real"],"instance":"c"}},
"der(c.v)":{"comment":"der(Voltage drop of the two pins (= p.v - n.v))","kind":"derivative","type":"Real","unit":"km2.s-4.A-1.g","displayUnit":"","source":{"info":{"file":"/usr/lib/omlibrary/Modelica 3.2.3/Electrical/Analog/Interfaces.mo","lineStart":172,"lineEnd":172,"colStart":5,"colEnd":62},"within":["Real"],"instance":"c"}},
"adaptor.u1":{"comment":"Optional 1st derivative of input","kind":"variable","type":"Real","unit":"","displayUnit":"","source":{"info":{"file":"/usr/lib/omlibrary/Modelica 3.2.3/Blocks/Interfaces.mo","lineStart":1723,"lineEnd":1723,"colStart":7,"colEnd":110},"within":["Real"],"instance":"adaptor"}},
"adaptor.y1":{"comment":"Optional 1st derivative of output","kind":"variable","type":"Real","unit":"","displayUnit":"","source":{"info":{"file":"/usr/lib/omlibrary/Modelica 3.2.3/Blocks/Interfaces.mo","lineStart":1720,"lineEnd":1720,"colStart":7,"colEnd":111},"within":["Real"],"instance":"adaptor"}},
"adaptor.y2":{"comment":"Optional 2nd derivative of output","kind":"variable","type":"Real","unit":"","displayUnit":"","source":{"info":{"file":"/usr/lib/omlibrary/Modelica 3.2.3/Blocks/Interfaces.mo","lineStart":1721,"lineEnd":1721,"colStart":7,"colEnd":111},"within":["Real"],"instance":"adaptor"}},
"gnd.p.i":{"comment":"Current flowing into the pin","kind":"variable","type":"Real","unit":"A","displayUnit":"","source":{"info":{"file":"/usr/lib/omlibrary/Modelica 3.2.3/Electrical/Analog/Interfaces.mo","lineStart":13,"lineEnd":18,"colStart":5,"colEnd":61},"within":["Real"],"instance":"gndp"}},
"gnd.p.v":{"comment":"Potential at the pin","kind":"variable","type":"Real","unit":"V","displayUnit":"","source":{"info":{"file":"/usr/lib/omlibrary/Modelica 3.2.3/Electrical/Analog/Interfaces.mo","lineStart":7,"lineEnd":12,"colStart":5,"colEnd":61},"within":["Real"],"instance":"gndp"}},
"i":{"comment":"","kind":"variable","type":"Real","unit":"","displayUnit":"","source":{"info":{"file":"/home/ubuntu/Scrivania/fmi-interface-cpp/FmiTest.mo","lineStart":4,"lineEnd":5,"colStart":5,"colEnd":195},"within":["Real"]}},
"r.LossPower":{"comment":"Loss power leaving component via heatPort","kind":"variable","type":"Real","unit":"W","displayUnit":"","source":{"info":{"file":"/usr/lib/omlibrary/Modelica 3.2.3/Electrical/Analog/Interfaces.mo","lineStart":312,"lineEnd":312,"colStart":5,"colEnd":67},"within":["Real"],"instance":"r"}},
"r.R_actual":{"comment":"Actual resistance = R*(1 + alpha*(T_heatPort - T_ref))","kind":"variable","type":"Real","unit":"Ohm","displayUnit":"","source":{"info":{"file":"/usr/lib/omlibrary/Modelica 3.2.3/Electrical/Analog/Basic.mo","lineStart":45,"lineEnd":46,"colStart":5,"colEnd":63},"within":["Real"],"instance":"r"}},
"r.v":{"comment":"Voltage drop of the two pins (= p.v - n.v)","kind":"variable","type":"Real","unit":"V","displayUnit":"","source":{"info":{"file":"/usr/lib/omlibrary/Modelica 3.2.3/Electrical/Analog/Interfaces.mo","lineStart":172,"lineEnd":172,"colStart":5,"colEnd":62},"within":["Real"],"instance":"r"}},
"v":{"comment":"","kind":"variable","type":"Real","unit":"","displayUnit":"","source":{"info":{"file":"/home/ubuntu/Scrivania/fmi-interface-cpp/FmiTest.mo","lineStart":6,"lineEnd":7,"colStart":5,"colEnd":193},"within":["Real"]}},
"v":{"comment":"","kind":"variable","type":"Real","unit":"","displayUnit":"","source":{"info":{"file":"/home/ubuntu/Scrivania/fmi-interface-cpp/FmiTest.mo","lineStart":6,"lineEnd":7,"colStart":5,"colEnd":193},"within":["Real"]}},
"c.C":{"comment":"Capacitance","kind":"parameter","type":"Real","unit":"F","displayUnit":"","source":{"info":{"file":"/usr/lib/omlibrary/Modelica 3.2.3/Electrical/Analog/Basic.mo","lineStart":224,"lineEnd":224,"colStart":5,"colEnd":54},"within":["Real"],"instance":"c"}},
"r.T":{"comment":"Fixed device temperature if useHeatPort = false","kind":"parameter","type":"Real","unit":"K","displayUnit":"degC","source":{"info":{"file":"/usr/lib/omlibrary/Modelica 3.2.3/Electrical/Analog/Interfaces.mo","lineStart":306,"lineEnd":307,"colStart":5,"colEnd":99},"within":["Real"],"instance":"r"}},
"r.T_heatPort":{"comment":"Temperature of heatPort","kind":"parameter","type":"Real","unit":"K","displayUnit":"degC","source":{"info":{"file":"/usr/lib/omlibrary/Modelica 3.2.3/Electrical/Analog/Interfaces.mo","lineStart":313,"lineEnd":313,"colStart":5,"colEnd":56},"within":["Real"],"instance":"r"}},
"r.T_ref":{"comment":"Reference temperature","kind":"parameter","type":"Real","unit":"K","displayUnit":"degC","source":{"info":{"file":"/usr/lib/omlibrary/Modelica 3.2.3/Electrical/Analog/Basic.mo","lineStart":39,"lineEnd":39,"colStart":5,"colEnd":66},"within":["Real"],"instance":"r"}},
"r.alpha":{"comment":"Temperature coefficient of resistance (R_actual = R*(1 + alpha*(T_heatPort - T_ref))","kind":"parameter","type":"Real","unit":"1/K","displayUnit":"","source":{"info":{"file":"/usr/lib/omlibrary/Modelica 3.2.3/Electrical/Analog/Basic.mo","lineStart":40,"lineEnd":41,"colStart":5,"colEnd":93},"within":["Real"],"instance":"r"}},
"adaptor.use_fder":{"comment":"Use output for 1st derivative of flow","kind":"parameter","type":"Boolean","unit":"","displayUnit":"","source":{"info":{"file":"/usr/lib/omlibrary/Modelica 3.2.3/Blocks/Interfaces.mo","lineStart":1692,"lineEnd":1693,"colStart":7,"colEnd":75},"within":["Boolean"],"instance":"adaptor"}},
"adaptor.use_pder":{"comment":"Use input for 1st derivative of potential","kind":"parameter","type":"Boolean","unit":"","displayUnit":"","source":{"info":{"file":"/usr/lib/omlibrary/Modelica 3.2.3/Blocks/Interfaces.mo","lineStart":1688,"lineEnd":1689,"colStart":7,"colEnd":75},"within":["Boolean"],"instance":"adaptor"}},
"adaptor.use_pder2":{"comment":"Use input for 2nd derivative of potential (only if 1st derivate is used, too)","kind":"parameter","type":"Boolean","unit":"","displayUnit":"","source":{"info":{"file":"/usr/lib/omlibrary/Modelica 3.2.3/Blocks/Interfaces.mo","lineStart":1690,"lineEnd":1691,"colStart":7,"colEnd":75},"within":["Boolean"],"instance":"adaptor"}},
"r.useHeatPort":{"comment":"=true, if heatPort is enabled","kind":"parameter","type":"Boolean","unit":"","displayUnit":"","source":{"info":{"file":"/usr/lib/omlibrary/Modelica 3.2.3/Electrical/Analog/Interfaces.mo","lineStart":304,"lineEnd":305,"colStart":5,"colEnd":71},"within":["Boolean"],"instance":"r"}}
},
"equations":[{"eqIndex":0,"tag":"dummy"},
{"eqIndex":1,"section":"initial","tag":"assign","defines":["adaptor.y1"],"uses":[],"equation":["0.0"],"source":{"info":{"file":"/usr/lib/omlibrary/Modelica 3.2.3/Blocks/Interfaces.mo","lineStart":1720,"lineEnd":1720,"colStart":7,"colEnd":111},"within":["Real"],"instance":"adaptor"}},
{"eqIndex":2,"section":"initial","tag":"assign","defines":["adaptor.y2"],"uses":[],"equation":["0.0"],"source":{"info":{"file":"/usr/lib/omlibrary/Modelica 3.2.3/Blocks/Interfaces.mo","lineStart":1721,"lineEnd":1721,"colStart":7,"colEnd":111},"within":["Real"],"instance":"adaptor"}},
{"eqIndex":3,"section":"initial","tag":"assign","defines":["adaptor.u1"],"uses":[],"equation":["0.0"],"source":{"info":{"file":"/usr/lib/omlibrary/Modelica 3.2.3/Blocks/Interfaces.mo","lineStart":1723,"lineEnd":1723,"colStart":7,"colEnd":110},"within":["Real"],"instance":"adaptor"}},
{"eqIndex":4,"section":"initial","tag":"assign","defines":["adaptor.u2"],"uses":[],"equation":["0.0"],"source":{"info":{"file":"/usr/lib/omlibrary/Modelica 3.2.3/Blocks/Interfaces.mo","lineStart":1724,"lineEnd":1724,"colStart":7,"colEnd":110},"within":["Real"],"instance":"adaptor"}},
{"eqIndex":5,"section":"initial","tag":"assign","defines":["gnd.p.i"],"uses":[],"equation":["0.0"],"source":{"info":{"file":"/usr/lib/omlibrary/Modelica 3.2.3/Electrical/Analog/Interfaces.mo","lineStart":13,"lineEnd":18,"colStart":5,"colEnd":61},"within":["Real"],"instance":"gndp"}},
{"eqIndex":6,"section":"initial","tag":"assign","defines":["c.v"],"uses":["$START.c.v"],"equation":["$START.c.v"],"source":{"info":{"file":"","lineStart":0,"lineEnd":0,"colStart":0,"colEnd":0}}},
{"eqIndex":7,"section":"initial","tag":"assign","defines":["r.R_actual"],"uses":["r.T_ref","r.T","r.alpha","r.R"],"equation":["r.R * (1.0 + r.alpha * (r.T - r.T_ref))"],"source":{"info":{"file":"/usr/lib/omlibrary/Modelica 3.2.3/Electrical/Analog/Basic.mo","lineStart":45,"lineEnd":46,"colStart":5,"colEnd":63},"within":["Real"],"instance":"r"}},
{"eqIndex":8,"tag":"alias","equation":[13],"section":"initial"},
{"eqIndex":9,"tag":"alias","equation":[14],"section":"initial"},
{"eqIndex":10,"tag":"alias","equation":[15],"section":"initial"},
{"eqIndex":11,"tag":"alias","equation":[16],"section":"initial"},
{"eqIndex":12,"section":"initial","tag":"assign","defines":["gnd.p.v"],"uses":[],"equation":["0.0"],"source":{"info":{"file":"/usr/lib/omlibrary/Modelica 3.2.3/Electrical/Analog/Interfaces.mo","lineStart":7,"lineEnd":12,"colStart":5,"colEnd":61},"within":["Real"],"instance":"gndp"}},
{"eqIndex":13,"section":"regular","tag":"assign","defines":["r.v"],"uses":["c.v","v"],"equation":["v - c.v"],"source":{"info":{"file":"/usr/lib/omlibrary/Modelica 3.2.3/Electrical/Analog/Interfaces.mo","lineStart":179,"lineEnd":179,"colStart":5,"colEnd":18},"within":["Modelica.Electrical.Analog.Basic.Resistor$r"],"instance":"r"}},
{"eqIndex":14,"section":"regular","tag":"assign","defines":["i"],"uses":["r.R_actual","r.v"],"equation":["r.v / r.R_actual"],"source":{"info":{"file":"/usr/lib/omlibrary/Modelica 3.2.3/Electrical/Analog/Basic.mo","lineStart":52,"lineEnd":52,"colStart":5,"colEnd":19},"within":["Modelica.Electrical.Analog.Basic.Resistor$r"],"instance":"r"}},
{"eqIndex":15,"section":"regular","tag":"assign","defines":["r.LossPower"],"uses":["i","r.v"],"equation":["r.v * i"],"source":{"info":{"file":"/usr/lib/omlibrary/Modelica 3.2.3/Electrical/Analog/Basic.mo","lineStart":53,"lineEnd":53,"colStart":5,"colEnd":20},"within":["Modelica.Electrical.Analog.Basic.Resistor$r"],"instance":"r"}},
{"eqIndex":16,"section":"regular","tag":"assign","defines":["der(c.v)"],"uses":["c.C","i"],"equation":["i / c.C"],"source":{"info":{"file":"/usr/lib/omlibrary/Modelica 3.2.3/Electrical/Analog/Basic.mo","lineStart":227,"lineEnd":227,"colStart":5,"colEnd":17},"within":["Modelica.Electrical.Analog.Basic.Capacitor$c"],"instance":"c"}},
{"eqIndex":17,"section":"regular","tag":"algorithm","equation":["assert(1.0 + r.alpha * (r.T - r.T_ref) >= 1e-15, \"Temperature outside scope of model!\");"],"source":{"info":{"file":"/usr/lib/omlibrary/Modelica 3.2.3/Electrical/Analog/Basic.mo","lineStart":49,"lineEnd":50,"colStart":5,"colEnd":45},"within":["Modelica.Electrical.Analog.Basic.Resistor$r"],"instance":"r"}},
{"eqIndex":18,"section":"parameter","tag":"assign","defines":["r.T"],"uses":["r.T_ref"],"equation":["r.T_ref"],"source":{"info":{"file":"/usr/lib/omlibrary/Modelica 3.2.3/Electrical/Analog/Interfaces.mo","lineStart":306,"lineEnd":307,"colStart":5,"colEnd":99},"within":["Real"],"instance":"r"}},
{"eqIndex":19,"section":"parameter","tag":"assign","defines":["r.T_heatPort"],"uses":["r.T"],"equation":["r.T"],"source":{"info":{"file":"/usr/lib/omlibrary/Modelica 3.2.3/Electrical/Analog/Interfaces.mo","lineStart":313,"lineEnd":313,"colStart":5,"colEnd":56},"within":["Real"],"instance":"r"}},
{"eqIndex":20,"section":"parameter","tag":"assign","defines":["r.useHeatPort"],"uses":[],"equation":["false"],"source":{"info":{"file":"/usr/lib/omlibrary/Modelica 3.2.3/Electrical/Analog/Interfaces.mo","lineStart":304,"lineEnd":305,"colStart":5,"colEnd":71},"within":["Boolean"],"instance":"r"}},
{"eqIndex":21,"section":"parameter","tag":"assign","defines":["adaptor.Name_fder2"],"uses":[],"equation":["\"d2i\""],"source":{"info":{"file":"/usr/lib/omlibrary/Modelica 3.2.3/Blocks/Interfaces.mo","lineStart":1718,"lineEnd":1718,"colStart":7,"colEnd":86},"within":["String"],"instance":"adaptor"}},
{"eqIndex":22,"section":"parameter","tag":"assign","defines":["adaptor.Name_fder"],"uses":[],"equation":["\"di\""],"source":{"info":{"file":"/usr/lib/omlibrary/Modelica 3.2.3/Blocks/Interfaces.mo","lineStart":1717,"lineEnd":1717,"colStart":7,"colEnd":84},"within":["String"],"instance":"adaptor"}},
{"eqIndex":23,"section":"parameter","tag":"assign","defines":["adaptor.Name_f"],"uses":[],"equation":["\"i\""],"source":{"info":{"file":"/usr/lib/omlibrary/Modelica 3.2.3/Blocks/Interfaces.mo","lineStart":1716,"lineEnd":1716,"colStart":7,"colEnd":58},"within":["String"],"instance":"adaptor"}},
{"eqIndex":24,"section":"parameter","tag":"assign","defines":["adaptor.Name_pder2"],"uses":[],"equation":["\"d2v\""],"source":{"info":{"file":"/usr/lib/omlibrary/Modelica 3.2.3/Blocks/Interfaces.mo","lineStart":1715,"lineEnd":1715,"colStart":7,"colEnd":91},"within":["String"],"instance":"adaptor"}},
{"eqIndex":25,"section":"parameter","tag":"assign","defines":["adaptor.Name_pder"],"uses":[],"equation":["\"dv\""],"source":{"info":{"file":"/usr/lib/omlibrary/Modelica 3.2.3/Blocks/Interfaces.mo","lineStart":1714,"lineEnd":1714,"colStart":7,"colEnd":89},"within":["String"],"instance":"adaptor"}},
{"eqIndex":26,"section":"parameter","tag":"assign","defines":["adaptor.Name_p"],"uses":[],"equation":["\"v\""],"source":{"info":{"file":"/usr/lib/omlibrary/Modelica 3.2.3/Blocks/Interfaces.mo","lineStart":1713,"lineEnd":1713,"colStart":7,"colEnd":63},"within":["String"],"instance":"adaptor"}},
{"eqIndex":27,"section":"parameter","tag":"assign","defines":["adaptor.use_fder2"],"uses":[],"equation":["false"],"source":{"info":{"file":"/usr/lib/omlibrary/Modelica 3.2.3/Blocks/Interfaces.mo","lineStart":1694,"lineEnd":1695,"colStart":7,"colEnd":75},"within":["Boolean"],"instance":"adaptor"}},
{"eqIndex":28,"section":"parameter","tag":"assign","defines":["adaptor.use_fder"],"uses":[],"equation":["false"],"source":{"info":{"file":"/usr/lib/omlibrary/Modelica 3.2.3/Blocks/Interfaces.mo","lineStart":1692,"lineEnd":1693,"colStart":7,"colEnd":75},"within":["Boolean"],"instance":"adaptor"}},
{"eqIndex":29,"section":"parameter","tag":"assign","defines":["adaptor.use_pder2"],"uses":[],"equation":["false"],"source":{"info":{"file":"/usr/lib/omlibrary/Modelica 3.2.3/Blocks/Interfaces.mo","lineStart":1690,"lineEnd":1691,"colStart":7,"colEnd":75},"within":["Boolean"],"instance":"adaptor"}},
{"eqIndex":30,"section":"parameter","tag":"assign","defines":["adaptor.use_pder"],"uses":[],"equation":["false"],"source":{"info":{"file":"/usr/lib/omlibrary/Modelica 3.2.3/Blocks/Interfaces.mo","lineStart":1688,"lineEnd":1689,"colStart":7,"colEnd":75},"within":["Boolean"],"instance":"adaptor"}},
{"eqIndex":31,"tag":"alias","equation":[12],"section":"parameter"},
{"eqIndex":32,"tag":"alias","equation":[7],"section":"parameter"},
{"eqIndex":33,"tag":"alias","equation":[5],"section":"parameter"},
{"eqIndex":34,"tag":"alias","equation":[4],"section":"parameter"},
{"eqIndex":35,"tag":"alias","equation":[3],"section":"parameter"},
{"eqIndex":36,"tag":"alias","equation":[2],"section":"parameter"},
{"eqIndex":37,"tag":"alias","equation":[1],"section":"parameter"},
{"eqIndex":38,"section":"parameter","tag":"algorithm","equation":["assert(r.T_ref >= 0.0, \"Variable violating min constraint: 0.0 <= r.T_ref, has value: \" + String(r.T_ref, \"g\"));"],"source":{"info":{"file":"/usr/lib/omlibrary/Modelica 3.2.3/Electrical/Analog/Basic.mo","lineStart":39,"lineEnd":39,"colStart":5,"colEnd":66},"within":["Real"],"instance":"r"}},
{"eqIndex":39,"section":"parameter","tag":"algorithm","equation":["assert(r.T >= 0.0, \"Variable violating min constraint: 0.0 <= r.T, has value: \" + String(r.T, \"g\"));"],"source":{"info":{"file":"/usr/lib/omlibrary/Modelica 3.2.3/Electrical/Analog/Interfaces.mo","lineStart":306,"lineEnd":307,"colStart":5,"colEnd":99},"within":["Real"],"instance":"r"}},
{"eqIndex":40,"section":"parameter","tag":"algorithm","equation":["assert(r.T_heatPort >= 0.0, \"Variable violating min constraint: 0.0 <= r.T_heatPort, has value: \" + String(r.T_heatPort, \"g\"));"],"source":{"info":{"file":"/usr/lib/omlibrary/Modelica 3.2.3/Electrical/Analog/Interfaces.mo","lineStart":313,"lineEnd":313,"colStart":5,"colEnd":56},"within":["Real"],"instance":"r"}},
{"eqIndex":41,"section":"parameter","tag":"algorithm","equation":["assert(c.C >= 0.0, \"Variable violating min constraint: 0.0 <= c.C, has value: \" + String(c.C, \"g\"));"],"source":{"info":{"file":"/usr/lib/omlibrary/Modelica 3.2.3/Electrical/Analog/Basic.mo","lineStart":224,"lineEnd":224,"colStart":5,"colEnd":54},"within":["Real"],"instance":"c"}}
],
"functions":[
]
}